instacreatorapi.py
instacreatorapi-0.0.2.dist-info/LICENSE
instacreatorapi-0.0.2.dist-info/METADATA
instacreatorapi-0.0.2.dist-info/WHEEL
instacreatorapi-0.0.2.dist-info/top_level.txt
instacreatorapi-0.0.2.dist-info/RECORD
