Metadata-Version: 2.1
Name: instacreatorapi
Version: 0.0.2
Summary: A Python module based on api to create Instagram Accounts
Home-page: https://github.com/godxgamer/Igcreatorapi
Author: god_x_gamer
Keywords: instagram,instacreatorapi,instagram account creatoraccount creator,instagram api,instagrapi
Classifier: Programming Language :: Python :: 3
Classifier: License :: OSI Approved :: MIT License
Classifier: Operating System :: OS Independent
Requires-Python: >=3.6
License-File: LICENSE
Requires-Dist: requests
